cmaes/__init__.py
cmaes/_catcma.py
cmaes/_cma.py
cmaes/_cmawm.py
cmaes/_dxnesic.py
cmaes/_sepcma.py
cmaes/_stats.py
cmaes/_warm_start.py
cmaes/_xnes.py
cmaes/cma.py
cmaes-0.11.1.dist-info/LICENSE
cmaes-0.11.1.dist-info/METADATA
cmaes-0.11.1.dist-info/WHEEL
cmaes-0.11.1.dist-info/top_level.txt
cmaes-0.11.1.dist-info/RECORD
