Metadata-Version: 2.1
Name: cmaes
Version: 0.11.1
Summary: Lightweight Covariance Matrix Adaptation Evolution Strategy (CMA-ES) implementation for Python 3.
Author-email: Masashi Shibata <m.shibata1020@gmail.com>
Maintainer-email: Masahiro Nomura <nomura_masahiro@cyberagent.co.jp>
License: MIT License
Project-URL: Homepage, https://github.com/CyberAgentAILab/cmaes
Classifier: Development Status :: 4 - Beta
Classifier: Intended Audience :: Developers
Classifier: License :: OSI Approved :: MIT License
Classifier: Programming Language :: Python
Classifier: Programming Language :: Python :: 3
Classifier: Programming Language :: Python :: 3.8
Classifier: Programming Language :: Python :: 3.9
Classifier: Programming Language :: Python :: 3.10
Classifier: Programming Language :: Python :: 3.11
Classifier: Programming Language :: Python :: 3.12
Classifier: Programming Language :: Python :: 3 :: Only
Classifier: Intended Audience :: Science/Research
Requires-Python: >=3.7
License-File: LICENSE
Requires-Dist: numpy
Provides-Extra: cmawm
Requires-Dist: scipy; extra == "cmawm"
